sochainer/__init__.py
sochainer/__main__.py
sochainer/sochain.py
sochainer-1.0.0.dist-info/LICENSE
sochainer-1.0.0.dist-info/METADATA
sochainer-1.0.0.dist-info/WHEEL
sochainer-1.0.0.dist-info/entry_points.txt
sochainer-1.0.0.dist-info/top_level.txt
sochainer-1.0.0.dist-info/RECORD
